maomao/__init__.py
maomao/__main__.py
maomao-0.0.3.dist-info/AUTHORS
maomao-0.0.3.dist-info/LICENSE
maomao-0.0.3.dist-info/METADATA
maomao-0.0.3.dist-info/WHEEL
maomao-0.0.3.dist-info/entry_points.txt
maomao-0.0.3.dist-info/top_level.txt
maomao-0.0.3.dist-info/RECORD
