Metadata-Version: 2.1
Name: maomao
Version: 0.0.3
Summary: TODO
Home-page: https://gitlab.com/nul.one/maomao
Author: Predrag Mandic
Author-email: predrag@nul.one
License: BSD
Download-URL: https://gitlab.com/nul.one/maomao/-/archive/0.0.3/maomao-0.0.3.tar.gz
Platform: UNKNOWN
Classifier: Development Status :: 4 - Beta
Classifier: Environment :: Console
Classifier: License :: OSI Approved :: BSD License
Classifier: Natural Language :: English
Classifier: Operating System :: POSIX :: Linux
Classifier: Programming Language :: Python :: 3 :: Only
Classifier: Topic :: Utilities
Requires-Python: >=3.4.6
Requires-Dist: clipboard (==0.0.4)
